{
  "_fv": 77,
  "_type": "recipe",
  "definition": {
    "recipeType": "Campfire cooking",
    "recipeRetstackSize": 1,
    "group": "cookedseeds",
    "cookingBookCategory": "MISC",
    "xpReward": 1.0,
    "cookingTime": 200,
    "craftingBookCategory": "MISC",
    "recipeShapeless": false,
    "campfireCookingInputStack": {
      "value": "CUSTOM:Weedseeds"
    },
    "campfireCookingReturnStack": {
      "value": "CUSTOM:CookedSeeds"
    },
    "name": "cooked_seeds_recipe_fire_camp",
    "namespace": "mod"
  }
}